{"id":"0K8wsPyo","poster":"Hide 0n Tree","date":"2017-12-22T14:33:38.023+0000","title":"Erkläre EUCH Schritt für Schritt wie man Counterdschungelt!","subforum":"Streams & YouTube","embed":{"title":"Explaining YOU Step by Step how to Counterjungle! | League of Legends Wukong Jungle Season 8","description":"There is no MY Jungle & Enemy Jungle...IT´S ALL MINE!! | Like' if you enjoyed & want MORE 💙 ► Help me reach 800 Subs!","url":"https://www.youtube.com/watch?v=D-NVBQZfYSY&t","image":"https://i.ytimg.com/vi/D-NVBQZfYSY/hqdefault.jpg"},"up_votes":1,"down_votes":1,"body":"Hallo Leute,\r\n\r\nIn diesem Video erkl&auml;re ich euch, wie man Counterdschungelt und den gegnerischen Dschungler aus dem Spiel nimmt. Ihr werdet in der Lage sein, viel Druck auszu&uuml;ben und die Art, wie ein Spiel l&auml;uft, zu &auml;ndern.","replies":[]}