{"id":"A8QQ4TNM","poster":"INF Safe","date":"2017-12-17T16:07:17.339+0000","title":"Suche noch einen Jungler ab Platin!","subforum":"Clans & Teams","up_votes":1,"down_votes":0,"body":"Hey! Wir sind gerade dabei ein neues Team aufzustellen, mit dem wir den neuen Modus,, Clash &quot; , Flex Q und auch evtl. auf anderen Turnieren in der neuen Season spielen wollen. Wenn du die Jgl Position mainst, mindestens Plat bist und ca. 18 + vom Alter bist dann schreib doch mich einfach an, unter dem Summonername INF Safe. Eine weitere Voraussetzung ist noch Teamspeak. Alles weiter kl&auml;ren wir dann. MFG Niklas aka INF Safe","replies":[]}