{"id":"QEqNdNOo","poster":"Twino","date":"2019-06-06T12:47:30.023+0000","title":"Plat 1 Support LF Duo","subforum":"Clans & Teams","embed":{"title":"Twino - Summoner Stats - League of Legends","description":"Twino / Platinum 1 21LP / 178W 131L Win Ratio 58% / Lulu - 27W 17L Win Ratio 61%, Rakan - 21W 18L Win Ratio 54%, Nami - 24W 12L Win Ratio 67%, Akali - 16W 19L Win Ratio 46%, Irelia - 16W 8L Win Ratio 67%","url":"https://euw.op.gg/summoner/userName=Twino","image":"http://opgg-static.akamaized.net/images/logo/2015/reverse.rectangle.png"},"up_votes":1,"down_votes":0,"body":"Heyo,\r\n\r\nwie der Titel bereits zeigt, suche ich einen Duo Partner. Ich bin Main Support, momentan Platin 1 (80% winrate).\r\nIch spiele momentan überwiegend Rakan, habe aber natürlich mehr Supporter zur Verfügung, bin da recht flexibel.\r\n\r\nAm besten wäre ein Midlaner oder Jungler, aber an sich ist es mir egal, welche Lane du spielst, solange du sie beherrscht!\r\n\r\nSonstige Anforderungen:\r\n\r\nKein Tilt &amp; Flame\r\nFokussiert bleiben, falls das Early mal schlecht läuft\r\nSpaß am Spiel\r\n18+\r\n\r\nIngame zu erreichen unter: Twino","replies":[]}