{"id":"YeuaeUq6","poster":"maybelucia","date":"2019-05-29T12:38:36.107+0000","title":"Suche wen für DuoQ!","subforum":"Clans & Teams","up_votes":1,"down_votes":0,"body":"Hallo! Ich bin Lucia, 19 Jahre alt &amp; meine main Rollen Mid und Supp. Leider kam ich diese Season noch nicht aktiv zum spielen und bin deshalb noch unranked, würde dies aber ändern. Letzte Season war ich Silber III und würde gerne wieder dahin kommen, wenn nicht sogar höher :D Da ich ungerne alleine spiele bräuchte ich wen der auch Lust hat etwas mit mir zu ranken. Am besten nicht zu sehr toxic sein und nicht krass tilten, es muss ja trotzdem noch Spaß machen.^^ Alsooo wenn du Lust hast kannst du mich einfach adden :)","replies":[]}