{"id":"6G4HfbZ5","poster":"IPMasters gUG","date":"2017-07-02T12:40:54.120+0000","title":"Support Main Sucht Team und Duo Q Partner","subforum":"Clans & Teams","up_votes":1,"down_votes":0,"body":"Guten Tag.\r\nIch suche ein Tryhardteam und einen Duo q Partner (optimal w&auml;re adc main).\r\nIch spiele Main Sup, bin 19 Jahre alt und war zum Ende der letzten Saison Platin 1 und habe ESL Erfahrung und Turnier Erfahrung. \r\nIch konnte aus gesundheitlichen Gr&uuml;nden leider die letzten 9-10 Monate kaum bis gar nicht zocken.\r\nSeit 2 Wochen spiele ich wieder Aktive und bin aktuell Platin 5 in Flex und Gold 5 solo q.\r\nMeine &quot;Main&quot; Champs sind {{champion:16}} {{champion:40}} . Allerdings &uuml;be ich gerade die Tank Supports und Rakan.\r\nBei Interesse bitte Melden. \r\nMit freundlichen Gr&uuml;&szlig;en","replies":[]}