{"id":"AGwfLHLb","poster":"Kata Ga Kill","date":"2017-03-19T14:48:31.714+0000","title":"Mondstaub Zauberklinge - In die Kluft?","subforum":"Champions & Gameplay","up_votes":1,"down_votes":1,"body":"Ich pers&ouml;nlich finde das Item {{item:3170}} toll und liefert f&uuml;r einige Tanky AP Dudes so ziemlich gute Allround Stats die manche gut gebrauchen können oder andere dringend f&uuml;r kleinen indirekten Buff ben&ouml;tigen.\n\n{{champion:50}} {{champion:31}} {{champion:131}} {{champion:84}} {{champion:1}} {{champion:63}} {{champion:69}} {{champion:245}} {{champion:60}} {{champion:28}} {{champion:79}} {{champion:127}} {{champion:55}} {{champion:7}} {{champion:82}} {{champion:25}} {{champion:76}} {{champion:13}} {{champion:163}} {{champion:8}} \n\nF&auml;nde es toll wenn die Mondklinge es in die Kluft schaffen w&uuml;rde.\n\nWas meint Ihr?","replies":[{"id":"","poster":"CCG Inu XIII","date":"2017-03-19T14:58:54.120+0000","up_votes":1,"down_votes":0,"body":"Ich kann dir garantieren, dass dann die Ap-Bruiser ausrasten allen voran Gragas Ekko und Diana. Und die ersten beiden sind schon stark genug. Du würdest im Endeffekt die richtigen Ap Assassins (Akali, Lb, Kat, Eve (Nida)) noch weiter in den Abgrund treiben und Dinge wie Tank Ekko wieder populär machen. So gerne ich es hätte um endlich was nettes neues für Akali zu haben, würde ich dagegen stimmen.","replies":[]}]}