{"id":"Yy7wwq9h","poster":"Twitch VenemyTV","date":"2016-10-11T16:52:49.876+0000","title":"Recommended Itembuild auf Aram Item doppelt","subforum":"Melde einen Bug","up_votes":1,"down_votes":0,"body":"Hey,\r\n\r\nIch habe mal heute 1 Runde Aram gespielt und mir ist aufgefallen das beim Recommended Itembuild das Elixier 2 mal in der Liste steht hier ein screen dazu:  https://gyazo.com/a612b65d77e9e95ca01804d5a66b62e6\r\n\r\nDenke mal das es versehentlich dort hinzugef&uuml;gt wurde und denke mal das ihr (Riot) es &auml;ndert\r\n\r\nMit freundlichen Gr&uuml;&szlig;en\r\n\r\nFNC Ixbalanqu&eacute;","replies":[]}