{"id":"5UB4mXdi","poster":"xMudde","date":"2020-01-08T19:27:51.953+0000","title":"Draft Mode und Hextechtruhen","subforum":"Hilfe & Support","up_votes":1,"down_votes":0,"body":"Moin, mal eben eine Frage zum Draft Mode.\r\nMir ist gerade mal aufgefallen das ich in den normal Games überhaupt keine Bewertungen für meinen Champion am Ende des Spiels erhalte. \r\nIst das richtig so oder einfach nur ein Bug?\r\nIch wollte mir meine verbliebenen Hextech Truhen gerade freispielen, hab mein Spiel mit 17/0 abgeschlossen, allerdings überhaupt keinen Rang erhalten um überhaupt eine Truhe zu bekommen. \r\nDanke schonmal im Voraus für Antworten :D","replies":[]}