{"id":"5gAwEr0M","poster":"Support Penguin","date":"2016-06-06T13:05:07.929+0000","title":"Suche Partner! Bin S1 [Main Support/ Jungle]","subforum":"Clans & Teams","up_votes":1,"down_votes":0,"body":"Moin,\r\n\r\nich suche einen DuoQ Partner, der mit mir den Weg Richtung Platin angehen will.\r\n\r\nErstmal zu mir:\r\n- 17 Jahre jung, gehe noch zur Schule ;p \r\n- Wohnort: Hannover\r\n- Main Support/ Jungle -  {{champion:201}} {{champion:25}} {{champion:412}}  - {{champion:59}} {{champion:32}} {{champion:254}} \r\n\r\n- meistens online von 18:00 bis 21:15 Uhr, am Wochenende l&auml;nger\r\n- S1 ~ 20 LP , letzte Season Platin\r\n- _**Ziel f&uuml;r diese Season: Mind. Plat 5 !! **_\r\n\r\n- Ts3 Server + Whatts App vorhanden \r\n\r\n\r\nWas ich erwarte: \r\n- geistige Reife\r\n- Spielverst&auml;ndnis - Hidden Elo von mind. S1 --&gt; einfaches Elo Climben\r\n- Aktivit&auml;t (18:00 bis 21:30 meistens) , 2-3 games an einigen Tagen w&auml;ren sch&ouml;n \r\n- angemessener Championpool\r\n- Ts3 + [Whatts App]\r\n\r\nBei Interesse addet mich: \r\n\r\n_**Thresh Hook GOD**_  {{champion:412}}  {{item:2050}}","replies":[{"id":"","poster":"Support Penguin","date":"2016-06-06T14:30:20.493+0000","up_votes":1,"down_votes":0,"body":"push #2","replies":[]},{"id":"","poster":"Support Penguin","date":"2016-06-06T14:29:09.218+0000","up_votes":1,"down_votes":0,"body":"push #1","replies":[]}]}