{"id":"UEUPcPEQ","poster":"HamSoloMid","date":"2016-05-21T06:26:16.243+0000","title":"5 GODTIER JUNGLER FOR PATCH 6.10 - CARRY JUNGLE IS REAL - League of Legends","subforum":"Streams & YouTube","embed":{"title":"5 GODTIER JUNGLER FOR PATCH 6.10 - CARRY JUNGLE IS REAL - League of Legends","description":"MOST OP SOLOQ CARRY JUNGLER FOR PATCH 6.10 Rumble Jungle Guide: https://www.youtube.com/watch?v=9SE8JLO4uUw Information provided by Balutos - League of Legends ★ You liked the Clip? SUBSCRIBE →https://www.youtube.com/channel/UCNnyaI22fge5I6KHsKn0voA?sub_confirmation=1 ★ Twitter: https://twitter.com/BalutosLoL ★ Facebook: https://www.facebook.com/Balutos-723057551130408/","url":"https://youtu.be/7tVunWiVFwM","image":"https://i.ytimg.com/vi/7tVunWiVFwM/hqdefault.jpg"},"up_votes":2,"down_votes":1,"body":"Hallo Leute! P&uuml;nktlich kurz nach dem neuem Patch erscheint wie schon zu Patch 6.9 die Top 5 Jungler f&uuml;r den Patch 6.10! Es gibt 3 Neuk&ouml;mmlinge und 2 sind sind nach wie vor gleichbleibend! Schaut euch das Video doch bitte mal an und sagt mir eure Meinungen in den Video-Kommentaren!\r\n\r\nLiebe Gr&uuml;&szlig;e\r\n\r\nBalutos","replies":[]}