{"id":"zvFuJod0","poster":"DirtLlip","date":"2015-10-14T16:25:34.899+0000","title":"Team sucht Jungle","subforum":"Clans & Teams","up_votes":1,"down_votes":0,"body":"Wie schon im Titel erw&auml;hnt suchen wir ein Junger f&uuml;r regelm&auml;&szlig;ige Teamranks bzw. Training.\r\n\r\nzu uns :\r\n-Wir spielen seid ein paar Monaten zusammen und haben Team Erfahrungen\r\n-Top Lane --&gt; DirtRotzay - Gold ( 22 Jahre)\r\n-Mid Lane --&gt; Neverlucky QQ - Gold (24 Jahre)\r\n-Adc          --&gt; DirtLlip - Gold (18 jahre )\r\n-Support  --&gt; Cloner152 - Platin (20)\r\n\r\n\r\nWas fordern wir ? \r\n\r\n-Headset + Mic. \r\n-Zeit ( 17 uhr +)\r\n-18 Jahre +\r\n-Meta Picks beherrschen \r\n- evtl. Shotcalling \r\n-Gold\r\n-Kritik &Auml;u&szlig;erung /F&auml;hig \r\nBewerbung :\r\n\r\n1. Name (ingame) (real): \r\n2. Alter:                             \r\n3. Elo:                                \r\n4. Erfahrungen:                \r\n5. Wie viel Zeit bringst du mit ? :                                \r\n6. Ziele: \r\n7. Champs:\r\n\r\n\r\n{{champion:17}}","replies":[]}