{"id":"XT6Y2LBm","poster":"SeriousAerox","date":"2015-07-04T17:38:53.822+0000","title":"Ranked Team sucht Support","subforum":"Clans & Teams","up_votes":1,"down_votes":0,"body":"Unser Ranked Team sucht zurzeit nach einem Support Spieler der wei&szlig; was er tut als Support :)\r\n\r\nFolgendes m&uuml;sst Ihr mitbringen:\r\n\r\n- Teamf&auml;higkeit\r\n- Wardplacments\r\n- 18+\r\n- TS3\r\n- Gold 3 oder h&ouml;her\r\n- Spielerfahrung mit folgenden Champs:\r\n{{champion:12}} {{champion:89}} {{champion:412}} {{champion:25}} {{champion:40}} {{champion:117}} \r\n\r\nWas wir bieten:\r\n\r\n- TS3 Server\r\n- Erfahrung durch langes zusammenspielen\r\n- Gold 1 und h&ouml;her Solo MMR\r\n- Gro&szlig;er Champ pool\r\n- Aus verlorenen Games noch ein Win erzielen :D\r\n\r\nEinfach bei Interesse Ingame adden :)\r\n\r\nMit Freundlichen Gr&uuml;&szlig;en\r\nSeriousAerox","replies":[]}