{"id":"x6xpaZYd","poster":"TherasGi","date":"2015-03-19T17:47:53.360+0000","title":"Golden Ducks - Rankteam sucht Mid und ADC","subforum":"Clans & Teams","up_votes":1,"down_votes":0,"body":"Hallo,\n\ngesucht wird wie im Titel schon zu sehen ist ein Mid-Laner und einen ADC.\n\nWas du mitbringen solltest:\n\n- mindestens Platin im Solo q\n- Ü18\n- kein Geflame, Rager werden sofort gekickt und ersetzt\n- Viel Zeit, da wir mehrmals die Woche abends spielen wollen, um uns auch wirklich zu verbessern\n- Es sollte deine Main Position sein\n\nDas Team ist relativ neu und noch nicht perfekt eingespielt. Also wenn jemand schon Teamerfahrung hat, oder sich als Couch mit einbringen will, ist auch gerne gesehen.\n\nBei Interesse einfach adden.","replies":[]}