{"id":"JeglETfA","poster":"DerBöseDawg","date":"2015-03-13T16:28:02.676+0000","title":"Main Jungler Sucht Festen/Aktiven Partner Für DuoQ","subforum":"Clans & Teams","up_votes":1,"down_votes":0,"body":"Mein Name ist Rubens bin 20 Jahre Alt und bin main jungler.\r\n\r\nDu solltest min. 18 Jahre alt sein und Ts/Skype haben mit einem guten Mikro, \r\nwelche lane du spielst ist egal Hauptsache du bist kein flamer und hast spass am spiel.\r\nDu solltest auch High Bronze oder Silber sein.\r\nMeldet euch einfach bei mir \" DerBöseDawg \"  oder hinterlasst eine Nachricht.","replies":[]}