{"id":"EHosU1Bw","poster":"h4llo23","date":"2019-01-10T18:27:43.078+0000","title":"Kein key fragment seit über einem Jahr?","subforum":"Hilfe & Support","up_votes":1,"down_votes":0,"body":"Ich habe mittlerweile 28 Kisten und nur ein einziges Schl&uuml;sselfragment. Vor &uuml;ber einem Jahr hatte ich einen 2-w&ouml;chigen Ban, seitdem aber nichts dergleichen. Wisst ihr genauer woran das liegen k&ouml;nnte?","replies":[{"id":"","poster":"Larce","date":"2019-01-10T19:31:27.555+0000","up_votes":1,"down_votes":0,"body":"Hey,\n\nmehr Informationen darüber, wie du Schlüsselfragmente erhälst bzw. wovon dies Abhängt findest du in diesem Frag Riot Artikel: https://euw.leagueoflegends.com/de/news/community/q/frag-riot-ich-brauche-schlussel\n\nFreundliche Grüsse\nLarcce","replies":[]}]}