{"id":"nGduXpLm","poster":"ImmerAmSchummeln","date":"2018-11-26T16:57:41.206+0000","title":"Neuer Start/Clansuche","subforum":"Clans & Teams","up_votes":1,"down_votes":0,"body":"Moin zusammen,\r\n\r\nnach langer inaktivit&auml;t fange ich mal wieder mit LoL an.\r\n\r\nIch bin auf der Suche nach einen Team, Club oder einen Clan\r\nmit denen ich zusammen zocken kann und gemeinsam verbessern.\r\n\r\nIch beheersche 3 Lanes, Top, Mid und Support.\r\n\r\nMit guten Umgang mit Darius als Top Lane (Meisterschaft LvL 6)\r\n\r\nBin momentan auf der Silber Elo 3 und nat&uuml;rlich \r\nkann ich mich verbessern.\r\n\r\nZu mir:\r\n\r\nIch bin Berufst&auml;tig und bin meistens Abends Online,\r\nbin 30 Jahre alt, besitze TS, Discord und habe einen funktionierendes Headset.\r\n\r\nMir ist es sehr wichtig Spa&szlig; an Spiel zu haben.\r\n\r\nAm liebsten suche ich einen Team die Discord besitzen.\r\n\r\nIch freue mich auf eine R&uuml;ckantwort\r\n\r\nPS: Im Ingame findet ihr mich unter ImmerAmSchummeln.","replies":[]}