{"id":"hGAN37Ee","poster":"JVLESX","date":"2018-11-19T18:38:39.094+0000","title":"Suche nette Mitspieler (Bronze,Silver,Gold Elo) 17+ Jahre, KEINE FLAMER!","subforum":"Clans & Teams","up_votes":1,"down_votes":0,"body":"Hey mein Name ist Jules ich bin 21 Jahre alt und suche nette Mitspieler f&uuml;rs Ranked &amp; Normals. Ich spiele LoL seit 2014 und war damals im unteren Gold Elo Bereich gerankt. Momentan sehe ich mich selbst auf Silber bis Gold Elo, da ich lange nicht mehr gespielt habe und ich erst wieder ein wenig reinkommen muss.\r\n\r\nFalls ihr 17+ seid, keine Flamer (konstruktive Kritik ist erw&uuml;nscht) und Spa&szlig; am Spiel habt, d&uuml;rft ihr mich gerne adden! Achja und ihr solltet TS haben.","replies":[]}