{"id":"aj7fwKZP","poster":"beηgi","date":"2018-04-10T08:56:52.248+0000","title":"Jungle Main [LF] DuoQ Partner | S7 Peak P1 -HEUTE-","subforum":"Clans & Teams","up_votes":1,"down_votes":0,"body":"Hey!\n\nIch habe etwa 3 Wochen kein League mehr gespielt und habe heute wieder Lust ein paar Rankeds zu machen (also tryharden!). Bei mir lief SoloQ in der letzten Zeit nicht sehr gut. W&uuml;rde gerne ein paar OFA oder Arams spielen, bevors ernst wird. :D\n\nZu mir:\n\n- Wieder P5\n- Main Jungle {{champion:59}} {{champion:5}} {{champion:60}} {{champion:113}} {{champion:2}} {{champion:28}} \n\n- 20 Jahre alt\n\n- Nicht toxisch. :)\n\nZu dir:\n\n- Main Mid oder ADC\n- TS und/oder Discord vorhanden\n- 20+\n- Wei&szlig;t wie du deine Lane zu spielen hast und hast Makroverst&auml;ndnis\n- Freundlich^^\n\nAddet mich unter: soten ni zase :)\n\nLG","replies":[{"id":"","poster":"Sillvyan","date":"2018-04-10T10:57:19.899+0000","up_votes":1,"down_votes":0,"body":"Alloha, suchst du noch?","replies":[]}]}