{"id":"gz4AfZit","poster":"Scârlet","date":"2018-01-26T21:52:35.966+0000","title":"Midlane Main sucht Team Platin+","subforum":"Clans & Teams","embed":{"title":"Exspecial - Summoner Stats - League of Legends","description":"Exspecial / Platinum 4 100LP / 10W 8L Win Ratio 56% / Malzahar - 4W 2L Win Ratio 67%, Vladimir - 3W 0L Win Ratio 100%, Azir - 1W 1L Win Ratio 50%, Ryze - 1W 1L Win Ratio 50%, Taliyah - 0W 2L Win Ratio 0%","url":"http://euw.op.gg/summoner/userName=Exspecial","image":"http://opgg-static.akamaized.net/images/logo/2015/reverse.rectangle.png"},"up_votes":1,"down_votes":0,"body":"Moin,\r\nIch suche ein Platin+ Team mit denen man sich verbessern kann, deshalb suche ich kein Fun Team.\r\n\r\nKurz zu mir:\r\n- 19 Jahre alt\r\n- habe Teamerfahrung\r\n- Kritikf&auml;hig\r\n- suche ein Team auf langfristige Ebene\r\n- S7 Elo: Platin 2 Ziel: S8 Elo: Diamant\r\n-Main Champions: Azir, Corki, Malzahr, Xerath, Taliyah, Orianna, Ryze\r\n\r\nBei Interesse bitte bei mir Melden\r\nING: Exspecial\r\n\r\nSch&ouml;nen Tag noch :)","replies":[]}